shioaji_position_management/__init__.py
shioaji_position_management/shioaji_position_management.py
shioaji_position_management-1.0.6.dist-info/LICENSE
shioaji_position_management-1.0.6.dist-info/METADATA
shioaji_position_management-1.0.6.dist-info/WHEEL
shioaji_position_management-1.0.6.dist-info/top_level.txt
shioaji_position_management-1.0.6.dist-info/RECORD
