Metadata-Version: 2.1
Name: shioaji-position-management
Version: 1.0.6
Summary: An Extensions help you trading with Sinopac shioaji
Home-page: https://github.com/NickLin910221/shioaji_position_management
Author: NickLin910221
Author-email: nicklin910221@gmail.com
Project-URL: Bug Tracker, https://github.com/NickLin910221/Shioaji_Position_Management/issues
Keywords: shioaji
Classifier: Programming Language :: Python :: 3
Classifier: License :: OSI Approved :: MIT License
Classifier: Operating System :: OS Independent
Requires-Python: >=3.6
License-File: LICENSE
Requires-Dist: shioaji
Requires-Dist: loguru
